tkinter_qu/__init__.py
tkinter_qu/base/__init__.py
tkinter_qu/base/colors.py
tkinter_qu/base/important_variables.py
tkinter_qu/base/library_changer.py
tkinter_qu/base/utility_functions.py
tkinter_qu/gui_components/__init__.py
tkinter_qu/gui_components/button.py
tkinter_qu/gui_components/component.py
tkinter_qu/gui_components/dimensions.py
tkinter_qu/gui_components/drop_down_menu.py
tkinter_qu/gui_components/frame.py
tkinter_qu/gui_components/grid.py
tkinter_qu/gui_components/grid_items.py
tkinter_qu/gui_components/input_field.py
tkinter_qu/gui_components/pages.py
tkinter_qu/gui_components/titled_input_field.py
tkinter_qu/gui_components/vim_grid.py
tkinter_qu-1.0.22.dist-info/METADATA
tkinter_qu-1.0.22.dist-info/WHEEL
tkinter_qu-1.0.22.dist-info/RECORD
