Metadata-Version: 2.1
Name: tkinter_qu
Version: 1.0.22
Project-URL: Homepage, https://github.com/Micah-Ribbens/Tkinter-Qu
Author-email: Micah Ribbens <mdriself.lengthbbens22@outlook.com>
Classifier: License :: OSI Approved :: MIT License
Classifier: Operating System :: OS Independent
Classifier: Programming Language :: Python :: 3
Requires-Python: >=3.7
